upoqa/__init__.py
upoqa/solver.py
upoqa/version.py
upoqa/problems/__init__.py
upoqa/problems/biquad_form.py
upoqa/problems/problem_base.py
upoqa/problems/quad_form.py
upoqa/problems/s2mpj_wrapper.py
upoqa/problems/utils.py
upoqa/problems/weighted_trace_panelty.py
upoqa/tests/test_extra_fun.py
upoqa/tests/test_inputs.py
upoqa/tests/test_update_state.py
upoqa/tests/test_xform_bounds.py
upoqa/tests/test_xform_speedup.py
upoqa/utils/__init__.py
upoqa/utils/interp_set.py
upoqa/utils/manager.py
upoqa/utils/model.py
upoqa/utils/params.py
upoqa/utils/preprocess.py
upoqa/utils/projection.py
upoqa/utils/result.py
upoqa/utils/sub_solver.py
upoqa-1.0.1.dist-info/licenses/LICENSE
upoqa-1.0.1.dist-info/METADATA
upoqa-1.0.1.dist-info/WHEEL
upoqa-1.0.1.dist-info/top_level.txt
upoqa-1.0.1.dist-info/RECORD
