Metadata-Version: 2.4
Name: upoqa
Version: 1.0.1
Summary: A model-based derivative-free optimizer for unconstrained partially-separable problems.
Author-email: Yichuan Liu <liuyichuan2020@outlook.com>, Yingzhou Li <yingzhouli@fudan.edu.cn>
License-Expression: GPL-3.0-or-later
Project-URL: Homepage, https://github.com/Chitius/upoqa
Project-URL: Download, https://github.com/Chitius/upoqa/releases/
Keywords: mathematics,optimization,derivative free optimization,partially separable problem
Classifier: Programming Language :: Python :: 3.8
Classifier: Programming Language :: Python :: 3.9
Classifier: Programming Language :: Python :: 3.10
Classifier: Programming Language :: Python :: 3.11
Classifier: Programming Language :: Python :: 3.12
Classifier: Operating System :: OS Independent
Classifier: Operating System :: Microsoft :: Windows
Classifier: Operating System :: POSIX :: Linux
Classifier: Operating System :: MacOS
Classifier: Topic :: Scientific/Engineering :: Mathematics
Classifier: Topic :: Scientific/Engineering
Classifier: Typing :: Typed
Classifier: Framework :: Jupyter
Classifier: Intended Audience :: Science/Research
Requires-Python: >=3.8
License-File: LICENSE
Requires-Dist: numpy
Requires-Dist: scipy
Requires-Dist: tqdm
Provides-Extra: dev
Requires-Dist: matplotlib; extra == "dev"
Requires-Dist: IPython; extra == "dev"
Requires-Dist: termcolor; extra == "dev"
Provides-Extra: profile
Requires-Dist: numpy>=2.0.0; extra == "profile"
Requires-Dist: scipy>=1.11.0; extra == "profile"
Requires-Dist: matplotlib; extra == "profile"
Requires-Dist: IPython; extra == "profile"
Requires-Dist: termcolor; extra == "profile"
Requires-Dist: spsa; extra == "profile"
Requires-Dist: pdfo; extra == "profile"
Requires-Dist: nlopt; extra == "profile"
Requires-Dist: cobyqa; extra == "profile"
Requires-Dist: Py-BOBYQA; extra == "profile"
Requires-Dist: qiskit; extra == "profile"
Requires-Dist: qiskit-algorithms; extra == "profile"
Requires-Dist: scikit-quant; extra == "profile"
Requires-Dist: cma; extra == "profile"
Dynamic: license-file
